COPYING
MANIFEST.in
README.rst
setup.cfg
setup.py
bang/__init__.py
bang/cmd_bang.py
bang/config.py
bang/inventory.py
bang/resources.py
bang/stack.py
bang/util.py
bang/version.py
bang.egg-info/PKG-INFO
bang.egg-info/SOURCES.txt
bang.egg-info/dependency_links.txt
bang.egg-info/requires.txt
bang.egg-info/top_level.txt
bang/attributes/__init__.py
bang/attributes/ansible.py
bang/attributes/creds.py
bang/attributes/database.py
bang/attributes/loadbalancer.py
bang/attributes/logging.py
bang/attributes/rightscale.py
bang/attributes/secgroup.py
bang/attributes/server.py
bang/attributes/ssh_key.py
bang/attributes/tags.py
bang/deployers/__init__.py
bang/deployers/cloud.py
bang/deployers/default.py
bang/deployers/deployer.py
bang/providers/__init__.py
bang/providers/aws.py
bang/providers/bases.py
bang/providers/rs.py
bang/providers/hpcloud/__init__.py
bang/providers/hpcloud/load_balancer.py
bang/providers/hpcloud/reddwarf.py
bang/providers/hpcloud/v12/__init__.py
bang/providers/hpcloud/v12/nova_ext.py
bang/providers/openstack/__init__.py
bin/bang
etc/requirements.pip
examples/.directory
examples/aws/README.txt
examples/aws/aws_secgroups.yml
examples/aws/minimal_server.yml
examples/banger/README.txt
examples/banger/aws_banger.yml
examples/banger/playbooks/bang/deploy.yml
examples/banger/playbooks/python/install-pip.yml
examples/basic/README.txt
examples/basic/just_run_a_playbook.yml
examples/basic/common_modules/bash_module_template
examples/basic/playbooks/a_playbook.yml
examples/basic/playbooks/gather_facts.yml
examples/basic/playbooks/vars/secretish.yml
examples/graphdb/graphdb.yml
examples/graphdb/playbooks/graphservers.yml
examples/graphdb/playbooks/site.yml
examples/graphdb/playbooks/group_vars/all
examples/graphdb/playbooks/roles/common/tasks/main.yml
examples/graphdb/playbooks/roles/titan/tasks/main.yml
examples/graphdb/playbooks/roles/titan/templates/cassandra-env.sh.j2
examples/graphdb/playbooks/roles/titan/templates/rexster.sh.j2
examples/graphdb/playbooks/roles/titan/vars/main.yml
examples/hpcloud/README.txt
examples/hpcloud/hpcloud_secgroups.yml
examples/rightscale/simple_server.yml