Metadata-Version: 1.0
Name: bang
Version: 0.18
Summary: Server and cloud resource deployment automation
Home-page: https://github.com/fr33jc/bang
Author: fr33jc
Author-email: fr33jc@gmail.com
License: GPLv3
Platform: POSIX
